{
	"configurations" : 
	[
		{
			"directories" : 
			[
				{
					"build" : ".",
					"jsonFile" : "directory-.-Debug-d0094a50bb2071803777.json",
					"minimumCMakeVersion" : 
					{
						"string" : "3.27"
					},
					"projectIndex" : 0,
					"source" : ".",
					"targetIndexes" : 
					[
						0
					]
				}
			],
			"name" : "Debug",
			"projects" : 
			[
				{
					"directoryIndexes" : 
					[
						0
					],
					"name" : "Ch_15_Functions",
					"targetIndexes" : 
					[
						0
					]
				}
			],
			"targets" : 
			[
				{
					"directoryIndex" : 0,
					"id" : "Ch_15_Functions::@6890427a1f51a3e7e1df",
					"jsonFile" : "target-Ch_15_Functions-Debug-c4eae7f2db16ae8c4a76.json",
					"name" : "Ch_15_Functions",
					"projectIndex" : 0
				}
			]
		}
	],
	"kind" : "codemodel",
	"paths" : 
	{
		"build" : "F:/C++ Projects/Comp Sci Chapter Questions/Ch-15 Functions/cmake-build-debug",
		"source" : "F:/C++ Projects/Comp Sci Chapter Questions/Ch-15 Functions"
	},
	"version" : 
	{
		"major" : 2,
		"minor" : 6
	}
}
